delta_stream/__init__.py
delta_stream/_compute_deltas.py
delta_stream/_defaults.py
delta_stream/_errors.py
delta_stream/_finish_json.py
delta_stream/_generate_model.py
delta_stream/_model_builder.py
delta_stream/_parser_state.py
delta_stream/_schema.py
delta_stream/_types.py
delta_stream/stream_parser.py
delta_stream-0.1.6.dist-info/LICENSE
delta_stream-0.1.6.dist-info/METADATA
delta_stream-0.1.6.dist-info/WHEEL
delta_stream-0.1.6.dist-info/RECORD
