Metadata-Version: 2.3
Name: delta_stream
Version: 0.1.6
Summary: Efficient structured streaming for real-time LLM outputs
License: MIT
Keywords: json,stream,parser,delta,diff,pydantic,llm,ai,openai,claude,anthropic,streaming,structured data
Author: David Tokar
Author-email: 1413david@gmail.com
Requires-Python: >=3.10,<4.0
Classifier: Development Status :: 3 - Alpha
Classifier: Intended Audience :: Developers
Classifier: License :: OSI Approved :: MIT License
Classifier: Programming Language :: Python :: 3
Classifier: Programming Language :: Python :: 3.10
Classifier: Programming Language :: Python :: 3.11
Classifier: Programming Language :: Python :: 3.12
Classifier: Programming Language :: Python :: 3.13
Classifier: Topic :: Scientific/Engineering :: Artificial Intelligence
Classifier: Topic :: Software Development :: Libraries :: Python Modules
Classifier: Typing :: Typed
Requires-Dist: pydantic (>=2.0,<3.0)
Project-URL: Homepage, https://github.com/DavidTokar12/DeltaStream
Project-URL: Repository, https://github.com/DavidTokar12/DeltaStream
